[
  {
    "status": "purchased",
    "quantity": 5,
    "price": 35.04
  },
  {
    "status": "shipped",
    "quantity": 5,
    "price": 86.79
  },
  {
    "status": "purchased",
    "quantity": 2,
    "price": 3.61
  },
  {
    "status": "shipped",
    "quantity": 4,
    "price": 43.48
  },
  {
    "status": "purchased",
    "quantity": 6,
    "price": 41.86
  },
  {
    "status": "purchased",
    "quantity": 2,
    "price": 2.77
  },
  {
    "status": "purchased",
    "quantity": 2,
    "price": 49.66
  },
  {
    "status": "purchased",
    "quantity": 5,
    "price": 70.15
  },
  {
    "status": "shipped",
    "quantity": 7,
    "price": 61.37
  },
  {
    "status": "shipped",
    "quantity": 4,
    "price": 89.72
  },
  {
    "status": "shipped",
    "quantity": 10,
    "price": 21.67
  },
  {
    "status": "shipped",
    "quantity": 4,
    "price": 50.42
  },
  {
    "status": "shipped",
    "quantity": 1,
    "price": 43.09
  },
  {
    "status": "purchased",
    "quantity": 5,
    "price": 78.0
  },
  {
    "status": "purchased",
    "quantity": 5,
    "price": 25.81
  },
  {
    "status": "pending",
    "quantity": 2,
    "price": 50.81
  },
  {
    "status": "pending",
    "quantity": 10,
    "price": 66.31
  },
  {
    "status": "shipped",
    "quantity": 9,
    "price": 81.79
  },
  {
    "status": "purchased",
    "quantity": 5,
    "price": 29.2
  },
  {
    "status": "shipped",
    "quantity": 10,
    "price": 70.37
  },
  {
    "status": "purchased",
    "quantity": 3,
    "price": 20.89
  },
  {
    "status": "purchased",
    "quantity": 1,
    "price": 97.92
  },
  {
    "status": "purchased",
    "quantity": 10,
    "price": 88.49
  },
  {
    "status": "purchased",
    "quantity": 9,
    "price": 49.35
  },
  {
    "status": "shipped",
    "quantity": 10,
    "price": 49.73
  },
  {
    "status": "purchased",
    "quantity": 10,
    "price": 31.17
  },
  {
    "status": "purchased",
    "quantity": 3,
    "price": 98.8
  },
  {
    "status": "purchased",
    "quantity": 1,
    "price": 6.58
  },
  {
    "status": "purchased",
    "quantity": 4,
    "price": 81.67
  },
  {
    "status": "shipped",
    "quantity": 10,
    "price": 33.35
  },
  {
    "status": "purchased",
    "quantity": 3,
    "price": 20.81
  },
  {
    "status": "purchased",
    "quantity": 5,
    "price": 76.52
  },
  {
    "status": "shipped",
    "quantity": 4,
    "price": 48.82
  },
  {
    "status": "purchased",
    "quantity": 6,
    "price": 56.84
  },
  {
    "status": "shipped",
    "quantity": 9,
    "price": 28.08
  },
  {
    "status": "purchased",
    "quantity": 7,
    "price": 30.6
  },
  {
    "status": "shipped",
    "quantity": 5,
    "price": 43.68
  },
  {
    "status": "purchased",
    "quantity": 6,
    "price": 10.7
  },
  {
    "status": "shipped",
    "quantity": 7,
    "price": 22.49
  },
  {
    "status": "shipped",
    "quantity": 1,
    "price": 60.32
  },
  {
    "status": "purchased",
    "quantity": 8,
    "price": 68.05
  },
  {
    "status": "shipped",
    "quantity": 6,
    "price": 7.62
  },
  {
    "status": "purchased",
    "quantity": 3,
    "price": 60.01
  },
  {
    "status": "shipped",
    "quantity": 6,
    "price": 89.55
  },
  {
    "status": "shipped",
    "quantity": 1,
    "price": 1.88
  },
  {
    "status": "pending",
    "quantity": 4,
    "price": 8.65
  },
  {
    "status": "purchased",
    "quantity": 5,
    "price": 97.07
  },
  {
    "status": "purchased",
    "quantity": 9,
    "price": 50.67
  },
  {
    "status": "purchased",
    "quantity": 6,
    "price": 71.88
  },
  {
    "status": "shipped",
    "quantity": 2,
    "price": 51.06
  },
  {
    "status": "purchased",
    "quantity": 1,
    "price": 84.13
  },
  {
    "status": "shipped",
    "quantity": 9,
    "price": 21.23
  },
  {
    "status": "purchased",
    "quantity": 10,
    "price": 39.53
  },
  {
    "status": "purchased",
    "quantity": 7,
    "price": 8.26
  },
  {
    "status": "shipped",
    "quantity": 10,
    "price": 25.91
  },
  {
    "status": "purchased",
    "quantity": 9,
    "price": 38.24
  },
  {
    "status": "purchased",
    "quantity": 1,
    "price": 63.48
  },
  {
    "status": "purchased",
    "quantity": 7,
    "price": 37.65
  },
  {
    "status": "purchased",
    "quantity": 9,
    "price": 62.01
  },
  {
    "status": "pending",
    "quantity": 5,
    "price": 6.21
  },
  {
    "status": "purchased",
    "quantity": 8,
    "price": 75.85
  },
  {
    "status": "shipped",
    "quantity": 1,
    "price": 29.4
  },
  {
    "status": "shipped",
    "quantity": 2,
    "price": 11.22
  },
  {
    "status": "purchased",
    "quantity": 9,
    "price": 42.57
  },
  {
    "status": "shipped",
    "quantity": 5,
    "price": 54.64
  },
  {
    "status": "purchased",
    "quantity": 3,
    "price": 4.5
  },
  {
    "status": "purchased",
    "quantity": 2,
    "price": 14.58
  },
  {
    "status": "purchased",
    "quantity": 1,
    "price": 16.97
  },
  {
    "status": "shipped",
    "quantity": 2,
    "price": 43.02
  },
  {
    "status": "purchased",
    "quantity": 3,
    "price": 42.6
  },
  {
    "status": "purchased",
    "quantity": 9,
    "price": 54.08
  },
  {
    "status": "shipped",
    "quantity": 10,
    "price": 54.8
  },
  {
    "status": "purchased",
    "quantity": 3,
    "price": 20.04
  },
  {
    "status": "shipped",
    "quantity": 9,
    "price": 90.78
  },
  {
    "status": "purchased",
    "quantity": 2,
    "price": 88.39
  },
  {
    "status": "shipped",
    "quantity": 5,
    "price": 92.91
  },
  {
    "status": "pending",
    "quantity": 2,
    "price": 2.58
  },
  {
    "status": "purchased",
    "quantity": 6,
    "price": 76.31
  },
  {
    "status": "shipped",
    "quantity": 8,
    "price": 20.7
  },
  {
    "status": "shipped",
    "quantity": 7,
    "price": 74.63
  },
  {
    "status": "purchased",
    "quantity": 8,
    "price": 99.72
  },
  {
    "status": "purchased",
    "quantity": 10,
    "price": 25.7
  },
  {
    "status": "shipped",
    "quantity": 8,
    "price": 98.82
  },
  {
    "status": "shipped",
    "quantity": 9,
    "price": 64.03
  },
  {
    "status": "purchased",
    "quantity": 6,
    "price": 41.49
  },
  {
    "status": "shipped",
    "quantity": 9,
    "price": 74.19
  },
  {
    "status": "purchased",
    "quantity": 10,
    "price": 8.68
  },
  {
    "status": "purchased",
    "quantity": 10,
    "price": 23.54
  },
  {
    "status": "shipped",
    "quantity": 2,
    "price": 41.78
  },
  {
    "status": "purchased",
    "quantity": 5,
    "price": 99.57
  },
  {
    "status": "shipped",
    "quantity": 5,
    "price": 12.13
  },
  {
    "status": "purchased",
    "quantity": 4,
    "price": 73.18
  },
  {
    "status": "purchased",
    "quantity": 3,
    "price": 50.96
  },
  {
    "status": "purchased",
    "quantity": 6,
    "price": 43.96
  },
  {
    "status": "shipped",
    "quantity": 4,
    "price": 89.21
  },
  {
    "status": "shipped",
    "quantity": 7,
    "price": 12.03
  },
  {
    "status": "shipped",
    "quantity": 9,
    "price": 40.02
  },
  {
    "status": "purchased",
    "quantity": 4,
    "price": 94.0
  },
  {
    "status": "pending",
    "quantity": 3,
    "price": 97.58
  },
  {
    "status": "purchased",
    "quantity": 2,
    "price": 42.31
  },
  {
    "status": "purchased",
    "quantity": 5,
    "price": 35.04
  },
  {
    "status": "shipped",
    "quantity": 5,
    "price": 86.79
  },
  {
    "status": "purchased",
    "quantity": 2,
    "price": 3.61
  },
  {
    "status": "shipped",
    "quantity": 4,
    "price": 43.48
  },
  {
    "status": "purchased",
    "quantity": 6,
    "price": 41.86
  },
  {
    "status": "purchased",
    "quantity": 2,
    "price": 2.77
  },
  {
    "status": "purchased",
    "quantity": 2,
    "price": 49.66
  },
  {
    "status": "purchased",
    "quantity": 5,
    "price": 70.15
  },
  {
    "status": "shipped",
    "quantity": 7,
    "price": 61.37
  },
  {
    "status": "shipped",
    "quantity": 4,
    "price": 89.72
  },
  {
    "status": "shipped",
    "quantity": 10,
    "price": 21.67
  },
  {
    "status": "shipped",
    "quantity": 4,
    "price": 50.42
  },
  {
    "status": "shipped",
    "quantity": 1,
    "price": 43.09
  },
  {
    "status": "purchased",
    "quantity": 5,
    "price": 78.0
  },
  {
    "status": "purchased",
    "quantity": 5,
    "price": 25.81
  },
  {
    "status": "pending",
    "quantity": 2,
    "price": 50.81
  },
  {
    "status": "pending",
    "quantity": 10,
    "price": 66.31
  },
  {
    "status": "shipped",
    "quantity": 9,
    "price": 81.79
  },
  {
    "status": "purchased",
    "quantity": 5,
    "price": 29.2
  },
  {
    "status": "shipped",
    "quantity": 10,
    "price": 70.37
  },
  {
    "status": "purchased",
    "quantity": 3,
    "price": 20.89
  },
  {
    "status": "purchased",
    "quantity": 1,
    "price": 97.92
  },
  {
    "status": "purchased",
    "quantity": 10,
    "price": 88.49
  },
  {
    "status": "purchased",
    "quantity": 9,
    "price": 49.35
  },
  {
    "status": "shipped",
    "quantity": 10,
    "price": 49.73
  },
  {
    "status": "purchased",
    "quantity": 10,
    "price": 31.17
  },
  {
    "status": "purchased",
    "quantity": 3,
    "price": 98.8
  },
  {
    "status": "purchased",
    "quantity": 1,
    "price": 6.58
  },
  {
    "status": "purchased",
    "quantity": 4,
    "price": 81.67
  },
  {
    "status": "shipped",
    "quantity": 10,
    "price": 33.35
  },
  {
    "status": "purchased",
    "quantity": 3,
    "price": 20.81
  },
  {
    "status": "purchased",
    "quantity": 5,
    "price": 76.52
  },
  {
    "status": "shipped",
    "quantity": 4,
    "price": 48.82
  },
  {
    "status": "purchased",
    "quantity": 6,
    "price": 56.84
  },
  {
    "status": "shipped",
    "quantity": 9,
    "price": 28.08
  },
  {
    "status": "purchased",
    "quantity": 7,
    "price": 30.6
  },
  {
    "status": "shipped",
    "quantity": 5,
    "price": 43.68
  },
  {
    "status": "purchased",
    "quantity": 6,
    "price": 10.7
  },
  {
    "status": "shipped",
    "quantity": 7,
    "price": 22.49
  },
  {
    "status": "shipped",
    "quantity": 1,
    "price": 60.32
  },
  {
    "status": "purchased",
    "quantity": 8,
    "price": 68.05
  },
  {
    "status": "shipped",
    "quantity": 6,
    "price": 7.62
  },
  {
    "status": "purchased",
    "quantity": 3,
    "price": 60.01
  },
  {
    "status": "shipped",
    "quantity": 6,
    "price": 89.55
  },
  {
    "status": "shipped",
    "quantity": 1,
    "price": 1.88
  },
  {
    "status": "pending",
    "quantity": 4,
    "price": 8.65
  },
  {
    "status": "purchased",
    "quantity": 5,
    "price": 97.07
  },
  {
    "status": "purchased",
    "quantity": 9,
    "price": 50.67
  },
  {
    "status": "purchased",
    "quantity": 6,
    "price": 71.88
  },
  {
    "status": "shipped",
    "quantity": 2,
    "price": 51.06
  },
  {
    "status": "purchased",
    "quantity": 1,
    "price": 84.13
  },
  {
    "status": "shipped",
    "quantity": 9,
    "price": 21.23
  },
  {
    "status": "purchased",
    "quantity": 10,
    "price": 39.53
  },
  {
    "status": "purchased",
    "quantity": 7,
    "price": 8.26
  },
  {
    "status": "shipped",
    "quantity": 10,
    "price": 25.91
  },
  {
    "status": "purchased",
    "quantity": 9,
    "price": 38.24
  },
  {
    "status": "purchased",
    "quantity": 1,
    "price": 63.48
  },
  {
    "status": "purchased",
    "quantity": 7,
    "price": 37.65
  },
  {
    "status": "purchased",
    "quantity": 9,
    "price": 62.01
  },
  {
    "status": "pending",
    "quantity": 5,
    "price": 6.21
  },
  {
    "status": "purchased",
    "quantity": 8,
    "price": 75.85
  },
  {
    "status": "shipped",
    "quantity": 1,
    "price": 29.4
  },
  {
    "status": "shipped",
    "quantity": 2,
    "price": 11.22
  },
  {
    "status": "purchased",
    "quantity": 9,
    "price": 42.57
  },
  {
    "status": "shipped",
    "quantity": 5,
    "price": 54.64
  },
  {
    "status": "purchased",
    "quantity": 3,
    "price": 4.5
  },
  {
    "status": "purchased",
    "quantity": 2,
    "price": 14.58
  },
  {
    "status": "purchased",
    "quantity": 1,
    "price": 16.97
  },
  {
    "status": "shipped",
    "quantity": 2,
    "price": 43.02
  },
  {
    "status": "purchased",
    "quantity": 3,
    "price": 42.6
  },
  {
    "status": "purchased",
    "quantity": 9,
    "price": 54.08
  },
  {
    "status": "shipped",
    "quantity": 10,
    "price": 54.8
  },
  {
    "status": "purchased",
    "quantity": 3,
    "price": 20.04
  },
  {
    "status": "shipped",
    "quantity": 9,
    "price": 90.78
  },
  {
    "status": "purchased",
    "quantity": 2,
    "price": 88.39
  },
  {
    "status": "shipped",
    "quantity": 5,
    "price": 92.91
  },
  {
    "status": "pending",
    "quantity": 2,
    "price": 2.58
  },
  {
    "status": "purchased",
    "quantity": 6,
    "price": 76.31
  },
  {
    "status": "shipped",
    "quantity": 8,
    "price": 20.7
  },
  {
    "status": "shipped",
    "quantity": 7,
    "price": 74.63
  },
  {
    "status": "purchased",
    "quantity": 8,
    "price": 99.72
  },
  {
    "status": "purchased",
    "quantity": 10,
    "price": 25.7
  },
  {
    "status": "shipped",
    "quantity": 8,
    "price": 98.82
  },
  {
    "status": "shipped",
    "quantity": 9,
    "price": 64.03
  },
  {
    "status": "purchased",
    "quantity": 6,
    "price": 41.49
  },
  {
    "status": "shipped",
    "quantity": 9,
    "price": 74.19
  },
  {
    "status": "purchased",
    "quantity": 10,
    "price": 8.68
  },
  {
    "status": "purchased",
    "quantity": 10,
    "price": 23.54
  },
  {
    "status": "shipped",
    "quantity": 2,
    "price": 41.78
  },
  {
    "status": "purchased",
    "quantity": 5,
    "price": 99.57
  },
  {
    "status": "shipped",
    "quantity": 5,
    "price": 12.13
  },
  {
    "status": "purchased",
    "quantity": 4,
    "price": 73.18
  },
  {
    "status": "purchased",
    "quantity": 3,
    "price": 50.96
  },
  {
    "status": "purchased",
    "quantity": 6,
    "price": 43.96
  },
  {
    "status": "shipped",
    "quantity": 4,
    "price": 89.21
  },
  {
    "status": "shipped",
    "quantity": 7,
    "price": 12.03
  },
  {
    "status": "shipped",
    "quantity": 9,
    "price": 40.02
  },
  {
    "status": "purchased",
    "quantity": 4,
    "price": 94.0
  },
  {
    "status": "pending",
    "quantity": 3,
    "price": 97.58
  },
  {
    "status": "purchased",
    "quantity": 2,
    "price": 42.31
  },
  {
    "status": "purchased",
    "quantity": 5,
    "price": 35.04
  },
  {
    "status": "shipped",
    "quantity": 5,
    "price": 86.79
  },
  {
    "status": "purchased",
    "quantity": 2,
    "price": 3.61
  },
  {
    "status": "shipped",
    "quantity": 4,
    "price": 43.48
  },
  {
    "status": "purchased",
    "quantity": 6,
    "price": 41.86
  },
  {
    "status": "purchased",
    "quantity": 2,
    "price": 2.77
  },
  {
    "status": "purchased",
    "quantity": 2,
    "price": 49.66
  },
  {
    "status": "purchased",
    "quantity": 5,
    "price": 70.15
  },
  {
    "status": "shipped",
    "quantity": 7,
    "price": 61.37
  },
  {
    "status": "shipped",
    "quantity": 4,
    "price": 89.72
  },
  {
    "status": "shipped",
    "quantity": 10,
    "price": 21.67
  },
  {
    "status": "shipped",
    "quantity": 4,
    "price": 50.42
  },
  {
    "status": "shipped",
    "quantity": 1,
    "price": 43.09
  },
  {
    "status": "purchased",
    "quantity": 5,
    "price": 78.0
  },
  {
    "status": "purchased",
    "quantity": 5,
    "price": 25.81
  },
  {
    "status": "pending",
    "quantity": 2,
    "price": 50.81
  },
  {
    "status": "pending",
    "quantity": 10,
    "price": 66.31
  },
  {
    "status": "shipped",
    "quantity": 9,
    "price": 81.79
  },
  {
    "status": "purchased",
    "quantity": 5,
    "price": 29.2
  },
  {
    "status": "shipped",
    "quantity": 10,
    "price": 70.37
  },
  {
    "status": "purchased",
    "quantity": 3,
    "price": 20.89
  },
  {
    "status": "purchased",
    "quantity": 1,
    "price": 97.92
  },
  {
    "status": "purchased",
    "quantity": 10,
    "price": 88.49
  },
  {
    "status": "purchased",
    "quantity": 9,
    "price": 49.35
  },
  {
    "status": "shipped",
    "quantity": 10,
    "price": 49.73
  },
  {
    "status": "purchased",
    "quantity": 10,
    "price": 31.17
  },
  {
    "status": "purchased",
    "quantity": 3,
    "price": 98.8
  },
  {
    "status": "purchased",
    "quantity": 1,
    "price": 6.58
  },
  {
    "status": "purchased",
    "quantity": 4,
    "price": 81.67
  },
  {
    "status": "shipped",
    "quantity": 10,
    "price": 33.35
  },
  {
    "status": "purchased",
    "quantity": 3,
    "price": 20.81
  },
  {
    "status": "purchased",
    "quantity": 5,
    "price": 76.52
  },
  {
    "status": "shipped",
    "quantity": 4,
    "price": 48.82
  },
  {
    "status": "purchased",
    "quantity": 6,
    "price": 56.84
  },
  {
    "status": "shipped",
    "quantity": 9,
    "price": 28.08
  },
  {
    "status": "purchased",
    "quantity": 7,
    "price": 30.6
  },
  {
    "status": "shipped",
    "quantity": 5,
    "price": 43.68
  },
  {
    "status": "purchased",
    "quantity": 6,
    "price": 10.7
  },
  {
    "status": "shipped",
    "quantity": 7,
    "price": 22.49
  },
  {
    "status": "shipped",
    "quantity": 1,
    "price": 60.32
  },
  {
    "status": "purchased",
    "quantity": 8,
    "price": 68.05
  },
  {
    "status": "shipped",
    "quantity": 6,
    "price": 7.62
  },
  {
    "status": "purchased",
    "quantity": 3,
    "price": 60.01
  },
  {
    "status": "shipped",
    "quantity": 6,
    "price": 89.55
  },
  {
    "status": "shipped",
    "quantity": 1,
    "price": 1.88
  },
  {
    "status": "pending",
    "quantity": 4,
    "price": 8.65
  },
  {
    "status": "purchased",
    "quantity": 5,
    "price": 97.07
  },
  {
    "status": "purchased",
    "quantity": 9,
    "price": 50.67
  },
  {
    "status": "purchased",
    "quantity": 6,
    "price": 71.88
  },
  {
    "status": "shipped",
    "quantity": 2,
    "price": 51.06
  },
  {
    "status": "purchased",
    "quantity": 1,
    "price": 84.13
  },
  {
    "status": "shipped",
    "quantity": 9,
    "price": 21.23
  },
  {
    "status": "purchased",
    "quantity": 10,
    "price": 39.53
  },
  {
    "status": "purchased",
    "quantity": 7,
    "price": 8.26
  },
  {
    "status": "shipped",
    "quantity": 10,
    "price": 25.91
  },
  {
    "status": "purchased",
    "quantity": 9,
    "price": 38.24
  },
  {
    "status": "purchased",
    "quantity": 1,
    "price": 63.48
  },
  {
    "status": "purchased",
    "quantity": 7,
    "price": 37.65
  },
  {
    "status": "purchased",
    "quantity": 9,
    "price": 62.01
  },
  {
    "status": "pending",
    "quantity": 5,
    "price": 6.21
  },
  {
    "status": "purchased",
    "quantity": 8,
    "price": 75.85
  },
  {
    "status": "shipped",
    "quantity": 1,
    "price": 29.4
  },
  {
    "status": "shipped",
    "quantity": 2,
    "price": 11.22
  },
  {
    "status": "purchased",
    "quantity": 9,
    "price": 42.57
  },
  {
    "status": "shipped",
    "quantity": 5,
    "price": 54.64
  },
  {
    "status": "purchased",
    "quantity": 3,
    "price": 4.5
  },
  {
    "status": "purchased",
    "quantity": 2,
    "price": 14.58
  },
  {
    "status": "purchased",
    "quantity": 1,
    "price": 16.97
  },
  {
    "status": "shipped",
    "quantity": 2,
    "price": 43.02
  },
  {
    "status": "purchased",
    "quantity": 3,
    "price": 42.6
  },
  {
    "status": "purchased",
    "quantity": 9,
    "price": 54.08
  },
  {
    "status": "shipped",
    "quantity": 10,
    "price": 54.8
  },
  {
    "status": "purchased",
    "quantity": 3,
    "price": 20.04
  },
  {
    "status": "shipped",
    "quantity": 9,
    "price": 90.78
  },
  {
    "status": "purchased",
    "quantity": 2,
    "price": 88.39
  },
  {
    "status": "shipped",
    "quantity": 5,
    "price": 92.91
  },
  {
    "status": "pending",
    "quantity": 2,
    "price": 2.58
  },
  {
    "status": "purchased",
    "quantity": 6,
    "price": 76.31
  },
  {
    "status": "shipped",
    "quantity": 8,
    "price": 20.7
  },
  {
    "status": "shipped",
    "quantity": 7,
    "price": 74.63
  },
  {
    "status": "purchased",
    "quantity": 8,
    "price": 99.72
  },
  {
    "status": "purchased",
    "quantity": 10,
    "price": 25.7
  },
  {
    "status": "shipped",
    "quantity": 8,
    "price": 98.82
  },
  {
    "status": "shipped",
    "quantity": 9,
    "price": 64.03
  },
  {
    "status": "purchased",
    "quantity": 6,
    "price": 41.49
  },
  {
    "status": "shipped",
    "quantity": 9,
    "price": 74.19
  },
  {
    "status": "purchased",
    "quantity": 10,
    "price": 8.68
  },
  {
    "status": "purchased",
    "quantity": 10,
    "price": 23.54
  },
  {
    "status": "shipped",
    "quantity": 2,
    "price": 41.78
  },
  {
    "status": "purchased",
    "quantity": 5,
    "price": 99.57
  },
  {
    "status": "shipped",
    "quantity": 5,
    "price": 12.13
  },
  {
    "status": "purchased",
    "quantity": 4,
    "price": 73.18
  },
  {
    "status": "purchased",
    "quantity": 3,
    "price": 50.96
  },
  {
    "status": "purchased",
    "quantity": 6,
    "price": 43.96
  },
  {
    "status": "shipped",
    "quantity": 4,
    "price": 89.21
  },
  {
    "status": "shipped",
    "quantity": 7,
    "price": 12.03
  },
  {
    "status": "shipped",
    "quantity": 9,
    "price": 40.02
  },
  {
    "status": "purchased",
    "quantity": 4,
    "price": 94.0
  },
  {
    "status": "pending",
    "quantity": 3,
    "price": 97.58
  },
  {
    "status": "purchased",
    "quantity": 2,
    "price": 42.31
  }
]
